pyClimat/__init__.py
pyClimat/analysis.py
pyClimat/data.py
pyClimat/gtopo.py
pyClimat/plot_utils.py
pyClimat/plots.py
pyClimat/utils.py
pyClimat-0.0.1.dist-info/METADATA
pyClimat-0.0.1.dist-info/WHEEL
pyClimat-0.0.1.dist-info/top_level.txt
pyClimat-0.0.1.dist-info/RECORD
