Metadata-Version: 2.1
Name: pyClimat
Version: 0.0.1
Summary: Python package for climate model output analysis and visualization
Home-page: https://github.com/Dan-Boat/PyClimat
Author: Daniel Boateng
Author-email: dannboateng@gmail.com
License: MIT
Keywords: climate analysis,climate data visualization,eof,Cartopy,Xarray
Platform: UNKNOWN
Classifier: Development Status :: 1 - Planning
Classifier: Intended Audience :: Science/Research
Classifier: License :: OSI Approved :: MIT License
Classifier: Operating System :: POSIX :: Linux
Classifier: Programming Language :: Python :: 3
Classifier: Programming Language :: Python :: 3.4
Classifier: Programming Language :: Python :: 3.5
Classifier: Programming Language :: Python :: 3.6
Classifier: Programming Language :: Python :: 3.7
Classifier: Programming Language :: Python :: 3.8
Classifier: Programming Language :: Python :: 3.9
Requires-Dist: numpy
Requires-Dist: pandas
Requires-Dist: xarray
Requires-Dist: statsmodels
Requires-Dist: seaborn
Requires-Dist: sklearn
Requires-Dist: scipy
Requires-Dist: eofs
Requires-Dist: Cartopy
Requires-Dist: matplotlib
